<?xml version="1.0" encoding="UTF-8"?>
<objects serializationModel="Studio.02.02.00">
	<object class="AudioFile" id="{aff21c0c-89d7-4624-9a78-9162c741f47b}">
		<property name="assetPath">
			<value>Mortar/sfx_mortarFalling.wav</value>
		</property>
		<property name="frequencyInKHz">
			<value>44.0999985</value>
		</property>
		<property name="channelCount">
			<value>2</value>
		</property>
		<property name="length">
			<value>3.5877777777777777</value>
		</property>
		<relationship name="masterAssetFolder">
			<destination>{8ed98dbb-c62a-4e9d-9a82-add566e83598}</destination>
		</relationship>
	</object>
</objects>
